pysed
