Metadata-Version: 1.1
Name: pysed
Version: 0.7.3
Author: dslackw
Author-email: d zlatanidis at gmail com
Maintainer: dslackw
Maintainer-email: d zlatanidis at gmail com
Home-page: https://github.com/dslackw/pysed
Summary: CLI utility that parses and transforms text
Classifier: Development Status :: 3 - Alpha
Classifier: Environment :: Console
Classifier: License :: OSI Approved :: GNU General Public License v3 (GPLv3)
Classifier: Operating System :: Microsoft :: MS-DOS
Classifier: Operating System :: Microsoft :: Windows
Classifier: Operating System :: Microsoft :: Windows :: Windows 7
Classifier: Operating System :: Microsoft :: Windows :: Windows Vista
Classifier: Operating System :: Microsoft :: Windows :: Windows XP
Classifier: Operating System :: POSIX
Classifier: Operating System :: POSIX :: BSD :: BSD/OS
Classifier: Operating System :: POSIX :: BSD :: FreeBSD
Classifier: Operating System :: POSIX :: Linux
Classifier: Operating System :: POSIX :: Other
Classifier: Operating System :: Unix
Classifier: Programming Language :: Python
Classifier: Programming Language :: Python :: 2
Classifier: Programming Language :: Python :: 2.6
Classifier: Programming Language :: Python :: 2.7
Classifier: Programming Language :: Python :: 3
Classifier: Programming Language :: Python :: 3.0
Classifier: Programming Language :: Python :: 3.1
Classifier: Programming Language :: Python :: 3.2
Classifier: Programming Language :: Python :: 3.3
Classifier: Programming Language :: Python :: 3.4
Classifier: Topic :: Text Editors
Classifier: Topic :: Text Editors :: Documentation
Classifier: Topic :: Text Editors :: Text Processing
Classifier: Topic :: Text Editors :: Word Processors
Classifier: Topic :: Text Processing :: Filters
Classifier: Topic :: Text Processing :: General
Classifier: Topic :: Utilities
